{
  "platform": "yahoo_rushbuy",
  "keyword": "yahoo_rushbuy",
  "total_products": 45,
  "products": [
    {
      "title": "Crocs 卡駱馳 (中性鞋) Mega Crush經典光輪克駱格-207988",
      "price": 2360,
      "image_url": "https://s.yimg.com/zp/MerchandiseImages/C4A0413170-SP-17541414.jpg",
      "url": "https://tw.buy.yahoo.com/gdsale/gdsale.asp?gdid=11189373",
      "platform": "yahoo_rushbuy"
    },
    {
      "title": "(時時樂限定)【Philips飛利浦】官方直營 S3241 5D電動刮鬍刀/電鬍刀",
      "price": 2488,
      "image_url": "https://s.yimg.com/zp/MerchandiseImages/09FE66AFFE-SP-20492383.jpg",
      "url": "https://tw.buy.yahoo.com/gdsale/gdsale.asp?gdid=11683678&sw=ae49730bebf2ae28",
      "platform": "yahoo_rushbuy"
    },
    {
      "title": "【BHK’s】100%膠原蛋白粉 (3g/條；30條/盒)3盒組",
      "price": 1430,
      "image_url": "https://s.yimg.com/zp/MerchandiseImages/AB0216F7C4-SP-12331816.jpg",
      "url": "https://tw.buy.yahoo.com/gdsale/gdsale.asp?gdid=10266986",
      "platform": "yahoo_rushbuy"
    },
    {
      "title": "GIORDANO 男/女裝防曬抗UV輕薄外套 【超值任選】",
      "price": 909,
      "image_url": "https://s.yimg.com/zp/MerchandiseImages/2ff36e5b21-Gd-11681059.jpg",
      "url": "https://tw.buy.yahoo.com/gdsale/gdsale.asp?gdid=11681059",
      "platform": "yahoo_rushbuy"
    },
    {
      "title": "Nike Air Force 107 男鞋 白色 經典 簡約 皮革 休閒鞋 CW2288-111",
      "price": 2349,
      "image_url": "https://s.yimg.com/zp/MerchandiseImages/1885417835-SP-14729046.jpg",
      "url": "https://tw.buy.yahoo.com/gdsale/gdsale.asp?gdid=10716072",
      "platform": "yahoo_rushbuy"
    },
    {
      "title": "【LAC利維喜】3入組 Full-Cal優鎂鈣30包(膠原蛋白/檸檬酸鈣/維他命D/孕養調理/靈活關鍵)",
      "price": 1490,
      "image_url": "https://s.yimg.com/zp/MerchandiseImages/0c82eab65b-Gd-10562295.jpg",
      "url": "https://tw.buy.yahoo.com/gdsale/gdsale.asp?gdid=10562295",
      "platform": "yahoo_rushbuy"
    },
    {
      "title": "AOC 55型 4K QLED Google TV 智慧顯示器 55U8040 (不含安裝)",
      "price": 9999,
      "image_url": "https://s.yimg.com/zp/MerchandiseImages/2b40a5b5d6-Gd-11613713.jpg",
      "url": "https://tw.buy.yahoo.com/gdsale/gdsale.asp?gdid=11613713",
      "platform": "yahoo_rushbuy"
    },
    {
      "title": "【賠售出清】L'OCCITANE 歐舒丹 杏仁護手霜30ml",
      "price": 249,
      "image_url": "https://s.yimg.com/zp/MerchandiseImages/92EAC8DDB9-Gd-11198473.jpg",
      "url": "https://tw.buy.yahoo.com/gdsale/gdsale.asp?gdid=11198473",
      "platform": "yahoo_rushbuy"
    },
    {
      "title": "Louis Vuitton LV 路易威登 M82154 Ivy 皮革WOC斜背包(黑色)",
      "price": 63711,
      "image_url": "https://s.yimg.com/zp/MerchandiseImages/A5BFF268C8-Gd-11082250.jpg",
      "url": "https://tw.buy.yahoo.com/gdsale/gdsale.asp?gdid=11082250",
      "platform": "yahoo_rushbuy"
    },
    {
      "title": "SanSheng三勝 MIT台灣製智慧導流涼感排汗背心/無袖衫/V領短袖-6件組(M-XXL) [時時樂限定]",
      "price": 749,
      "image_url": "https://img.yec.tw/zp/MerchandiseImages/e9f64ca23d-Gd-11685679.jpg",
      "url": "https://tw.buy.yahoo.com/gdsale/gdsale.asp?gdid=11685679",
      "platform": "yahoo_rushbuy"
    },
    {
      "title": "舒潔 棉柔厚韌(三層)抽取衛生紙 110抽X30包/箱",
      "price": 579,
      "image_url": "https://s.yimg.com/zp/MerchandiseImages/0e6757caa2-Gd-11121603.jpg",
      "url": "https://tw.buy.yahoo.com/gdsale/gdsale.asp?gdid=11121603",
      "platform": "yahoo_rushbuy"
    },
    {
      "title": "法國公雞牌 網路獨家 休閒短袖T恤 男女款 多款任選",
      "price": 739,
      "image_url": "https://s.yimg.com/zp/MerchandiseImages/593bb36200-Gd-11624661.jpg",
      "url": "https://tw.buy.yahoo.com/gdsale/gdsale.asp?gdid=11624661",
      "platform": "yahoo_rushbuy"
    },
    {
      "title": "【大研生醫】綜合維他命緩釋膜衣錠 (60錠)x5",
      "price": 1680,
      "image_url": "https://s.yimg.com/zp/MerchandiseImages/09d02d7d18-Gd-9460466.jpg",
      "url": "https://tw.buy.yahoo.com/gdsale/gdsale.asp?gdid=9460466",
      "platform": "yahoo_rushbuy"
    },
    {
      "title": "【Adidas 愛迪達】ADIZERO BOSTON 13 M 慢跑鞋 運動鞋 男女 A-JR4791 B-JS4932 C-JS4938 D-JS4950 精選六款",
      "price": 2500,
      "image_url": "https://s.yimg.com/zp/MerchandiseImages/5eac746a44-Gd-11665724.jpg",
      "url": "https://tw.buy.yahoo.com/gdsale/gdsale.asp?gdid=11665724",
      "platform": "yahoo_rushbuy"
    },
    {
      "title": "【毛孩時代】腸胃專科益生菌x10盒(貓狗益生菌 貓狗腸胃保健)",
      "price": 4600,
      "image_url": "https://s.yimg.com/zp/MerchandiseImages/804b8a6a2b-Gd-9118249.jpg",
      "url": "https://tw.buy.yahoo.com/gdsale/gdsale.asp?gdid=9118249",
      "platform": "yahoo_rushbuy"
    },
    {
      "title": "倍麗森Beroso 無線充電版可替換頭溫熱按摩刮痧美體機A00021拔罐機 推拿儀 經絡儀 舒眠小物",
      "price": 688,
      "image_url": "https://s.yimg.com/zp/MerchandiseImages/457B77D22C-Product-23663215.jpg",
      "url": "https://tw.buy.yahoo.com/gdsale/gdsale.asp?gdid=8480481",
      "platform": "yahoo_rushbuy"
    },
    {
      "title": "萬歲牌 熱銷堅果罐 8款任選2罐超值組",
      "price": 540,
      "image_url": "https://s.yimg.com/zp/MipImages/5870E3CB7F-MIP-667756.jpeg",
      "url": "https://tw.buy.yahoo.com/activity/onsale/combo?actid=667756",
      "platform": "yahoo_rushbuy"
    },
    {
      "title": "【美國康寧】(2入組) SNAPWARE 鋅light輕瓷保溫保冰隨行杯750ml",
      "price": 1080,
      "image_url": "https://s.yimg.com/zp/MerchandiseImages/4ad9a6b49f-Gd-11650576.jpg",
      "url": "https://tw.buy.yahoo.com/gdsale/gdsale.asp?gdid=11650576",
      "platform": "yahoo_rushbuy"
    },
    {
      "title": "sebamed施巴 油性洗髮乳1000ml 2入組",
      "price": 1439,
      "image_url": "https://s.yimg.com/zp/MerchandiseImages/22C7EF737A-Gd-6670574.jpg",
      "url": "https://tw.buy.yahoo.com/gdsale/gdsale.asp?gdid=6670574",
      "platform": "yahoo_rushbuy"
    },
    {
      "title": "Lenovo Idea Tab Pro TB373FU 12.7吋平板電腦 (8G/256G)",
      "price": 13990,
      "image_url": "https://s.yimg.com/zp/MerchandiseImages/603E5EF216-SP-18975278.jpg",
      "url": "https://tw.buy.yahoo.com/gdsale/gdsale.asp?gdid=11485378",
      "platform": "yahoo_rushbuy"
    },
    {
      "title": "爆款1日下殺【WEDAR薇達】 金盞花葉黃素x6盒 (網路限定版)",
      "price": 899,
      "image_url": "https://s.yimg.com/zp/MerchandiseImages/89cbe4eabc-Gd-10894366.jpg",
      "url": "https://tw.buy.yahoo.com/gdsale/gdsale.asp?gdid=10894366",
      "platform": "yahoo_rushbuy"
    },
    {
      "title": "Seagate Ultra Touch 4TB 外接硬碟-卵石灰(STMA4000400)",
      "price": 3788,
      "image_url": "https://s.yimg.com/zp/MerchandiseImages/949787AF1A-SP-20250613.jpg",
      "url": "https://tw.buy.yahoo.com/gdsale/gdsale.asp?gdid=11646854",
      "platform": "yahoo_rushbuy"
    },
    {
      "title": "【時時樂限定】Just J'S Miss 精選春夏商品獨家限時優惠價 $518",
      "price": 518,
      "image_url": "https://s.yimg.com/zp/MerchandiseImages/feaa0fdf08-Gd-11679520.jpg",
      "url": "https://tw.buy.yahoo.com/gdsale/gdsale.asp?gdid=11679520",
      "platform": "yahoo_rushbuy"
    },
    {
      "title": "ANDYMAY2 (100入) ABS無痕防滑衣架 OH-T107【曬衣架 衣架 褲架 吊衣架 掛衣架 內衣架】(時時樂限定)",
      "price": 480,
      "image_url": "https://s.yimg.com/zp/MerchandiseImages/B62BDCDD9B-SP-18709039.jpg",
      "url": "https://tw.buy.yahoo.com/gdsale/gdsale.asp?gdid=11440991",
      "platform": "yahoo_rushbuy"
    },
    {
      "title": "愛心暑期食物箱7件組【受贈對象：安得烈慈善協會 】(您不會收到商品) (公益)",
      "price": 675,
      "image_url": "https://s.yimg.com/zp/MerchandiseImages/B207C452E0-SP-20041217.jpg",
      "url": "https://tw.buy.yahoo.com/gdsale/gdsale.asp?gdid=11615587",
      "platform": "yahoo_rushbuy"
    },
    {
      "title": "【賠售出清】NARS 裸光蜜粉餅 10g",
      "price": 750,
      "image_url": "https://s.yimg.com/zp/MerchandiseImages/F26F307C2D-SP-18599872.jpg",
      "url": "https://tw.buy.yahoo.com/gdsale/gdsale.asp?gdid=11411053",
      "platform": "yahoo_rushbuy"
    },
    {
      "title": "羅技 MX Anywhere 3S 無線行動滑鼠(黑\\白\\粉)",
      "price": 2490,
      "image_url": "https://s.yimg.com/zp/MerchandiseImages/6B9F9E35A1-Product-34977450.jpg",
      "url": "https://tw.buy.yahoo.com/gdsale/gdsale.asp?gdid=11088349",
      "platform": "yahoo_rushbuy"
    },
    {
      "title": "【時時樂限定★】金安德森-男裝經典襯衫(多款新品任選)",
      "price": 688,
      "image_url": "https://s.yimg.com/zp/MerchandiseImages/2BFAD772D4-SP-20502057.jpg",
      "url": "https://tw.buy.yahoo.com/gdsale/gdsale.asp?gdid=11685398",
      "platform": "yahoo_rushbuy"
    },
    {
      "title": "ALUXE 亞立詩 18K金 鑽石項鍊 弧形時光 NN0954",
      "price": 5450,
      "image_url": "https://s.yimg.com/zp/MerchandiseImages/2665F8D464-SP-13901864.jpg",
      "url": "https://tw.buy.yahoo.com/gdsale/gdsale.asp?gdid=10596397",
      "platform": "yahoo_rushbuy"
    },
    {
      "title": "高露潔 抗敏專家牙膏超值7入",
      "price": 791,
      "image_url": "https://s.yimg.com/zp/MerchandiseImages/7b43dc7822-Gd-9043863.jpg",
      "url": "https://tw.buy.yahoo.com/gdsale/gdsale.asp?gdid=9043863",
      "platform": "yahoo_rushbuy"
    },
    {
      "title": "INJA IJ20 超微聲專業錄音筆32G",
      "price": 1199,
      "image_url": "https://s.yimg.com/zp/MerchandiseImages/d718978389-Gd-11670557.jpg",
      "url": "https://tw.buy.yahoo.com/gdsale/gdsale.asp?gdid=11670557",
      "platform": "yahoo_rushbuy"
    },
    {
      "title": "船井 牛奶鈣魚膠原粉10入/盒x10+送牛奶鈣魚膠原粉1入x5(共105包)-高成長三效配方_速",
      "price": 4699,
      "image_url": "https://img.yec.tw/zp/MerchandiseImages/106ec3dfb4-Gd-11568693.jpg",
      "url": "https://tw.buy.yahoo.com/gdsale/gdsale.asp?gdid=11568693",
      "platform": "yahoo_rushbuy"
    },
    {
      "title": "【杏輝醫藥】蓉憶記膠囊 健字號x3盒 (共90粒)",
      "price": 5800,
      "image_url": "https://s.yimg.com/zp/MerchandiseImages/00a4f8f876-Gd-10298773.jpg",
      "url": "https://tw.buy.yahoo.com/gdsale/gdsale.asp?gdid=10298773",
      "platform": "yahoo_rushbuy"
    },
    {
      "title": "【安伯特】神波源 太極K5紫外線負離子 車用空氣清淨機 USB供電 紫外線殺菌 買就送濾網x2",
      "price": 1388,
      "image_url": "https://s.yimg.com/zp/MerchandiseImages/24E14C62B9-SP-13792811.jpg",
      "url": "https://tw.buy.yahoo.com/gdsale/gdsale.asp?gdid=10558868",
      "platform": "yahoo_rushbuy"
    },
    {
      "title": "【PP石墨烯】石墨烯塑崩褲氣動版_限量色1件(循環透氣塑身褲)",
      "price": 2580,
      "image_url": "https://img.yec.tw/zp/MerchandiseImages/5a453120a0-Gd-10914488.jpg",
      "url": "https://tw.buy.yahoo.com/gdsale/gdsale.asp?gdid=10914488",
      "platform": "yahoo_rushbuy"
    },
    {
      "title": "2年保固 ONPRO UC-GAN65W 氮化鎵GaN 65W 3孔PD快充充電器",
      "price": 499,
      "image_url": "https://s.yimg.com/zp/MerchandiseImages/5F39906454-SP-10615452.jpg",
      "url": "https://tw.buy.yahoo.com/gdsale/gdsale.asp?gdid=9767979",
      "platform": "yahoo_rushbuy"
    },
    {
      "title": "GOLDWELL 歌薇 光感 柔感洗髮精/髮膜 1000ml多款任選",
      "price": 899,
      "image_url": "https://s.yimg.com/zp/MerchandiseImages/C068E44835-Gd-11177782.jpg",
      "url": "https://tw.buy.yahoo.com/gdsale/gdsale.asp?gdid=11177782",
      "platform": "yahoo_rushbuy"
    },
    {
      "title": "CITIZEN 星辰 Chronograph 極速捕手光動能計時錶-CA4534-81XR",
      "price": 5980,
      "image_url": "https://s.yimg.com/zp/MerchandiseImages/3F9DA7F9CA-SP-19641229.jpg",
      "url": "https://tw.buy.yahoo.com/gdsale/gdsale.asp?gdid=11576290",
      "platform": "yahoo_rushbuy"
    },
    {
      "title": "【韓國熊津】(買二送二) 紅蔘飲-原味Ｘ4盒 (70mlx8入)",
      "price": 1104,
      "image_url": "https://s.yimg.com/zp/MerchandiseImages/a259639f82-Gd-11538728.jpg",
      "url": "https://tw.buy.yahoo.com/gdsale/gdsale.asp?gdid=11538728",
      "platform": "yahoo_rushbuy"
    },
    {
      "title": "奈米防水防汙噴霧 300ml【德國Bufalo布法羅】",
      "price": 449,
      "image_url": "https://s.yimg.com/zp/MerchandiseImages/A272EF2CF9-SP-7653717.jpg",
      "url": "https://tw.buy.yahoo.com/gdsale/gdsale.asp?gdid=8677738",
      "platform": "yahoo_rushbuy"
    },
    {
      "title": "家樂福商品提貨券總面額$20000",
      "price": 19700,
      "image_url": "https://s.yimg.com/zp/MerchandiseImages/8F00C1F907-Gd-9655291.jpg",
      "url": "https://tw.buy.yahoo.com/gdsale/gdsale.asp?gdid=9655291",
      "platform": "yahoo_rushbuy"
    },
    {
      "title": "【苗栗南庄鄉農會】有機黑木耳露(350mlx24入/箱)-原味/紅棗",
      "price": 588,
      "image_url": "https://s.yimg.com/zp/MerchandiseImages/61cc370ad4-Gd-10939896.jpg",
      "url": "https://tw.buy.yahoo.com/gdsale/gdsale.asp?gdid=10939896",
      "platform": "yahoo_rushbuy"
    },
    {
      "title": "【DUYAN 竹漾】Cool-Fi 瞬間涼感6D冰涼墊 / 單人/雙人/雙人加大 / 多款任選 均一價",
      "price": 788,
      "image_url": "https://s.yimg.com/zp/MerchandiseImages/2B1A3F0DF6-SP-20469303.jpg",
      "url": "https://tw.buy.yahoo.com/gdsale/gdsale.asp?gdid=11679260",
      "platform": "yahoo_rushbuy"
    },
    {
      "title": "【韓國鍾根堂 LACTO-FIT】GOLD 益生菌粉末食品 大童與成人款 2g/120入/罐",
      "price": 800,
      "image_url": "https://s.yimg.com/zp/MerchandiseImages/C657B98D6C-SP-13867134.jpg",
      "url": "https://tw.buy.yahoo.com/gdsale/gdsale.asp?gdid=10571541",
      "platform": "yahoo_rushbuy"
    },
    {
      "title": "【Glolux北美品牌】 miniQ 2L 健康無油氣炸鍋-經典奶茶(AF2100)",
      "price": 899,
      "image_url": "https://s.yimg.com/zp/MerchandiseImages/8A33C37083-SP-17051466.jpg",
      "url": "https://tw.buy.yahoo.com/gdsale/gdsale.asp?gdid=11099124",
      "platform": "yahoo_rushbuy"
    }
  ],
  "crawl_time": "2025-07-11 07:25:36"
}